{
  "slug": "mindfulness-for-new-parents",
  "title": "Mindfulness for New Parents — Starting Small",
  "category": "health",
  "subcategory": "Mental Health",
  "stage": "first-year",
  "audience": "both",
  "summary": "You don't have time for a 30-minute meditation practice — we know. This guide is built around 2–5 minute techniques that work in the middle of a feed, a nappy change, or a sleepless 3am.",
  "tags": [
    "mindfulness",
    "meditation",
    "stress",
    "new parent",
    "calm"
  ],
  "affiliateUrl": "",
  "affiliateLabel": "",
  "imageUrl": "https://images.unsplash.com/photo-1573496359142-b8d87734a5a2?w=800&q=80",
  "readingTime": "4 min read",
  "publishedAt": "2026-03-24T00:00:00.000Z",
  "draft": false,
  "body": "<h2>The Usual Advice Doesn&#39;t Fit</h2>\n<p>Most mindfulness guidance assumes you have time — time to sit quietly, to follow a guided session, to establish a routine. In the newborn phase, that assumption doesn&#39;t hold. You have gaps of 10–20 minutes between demands, if you&#39;re lucky, and those gaps are competed for by eating, sleeping, and showering.</p>\n<p>This guide is built around micro-practices: techniques that take 2–5 minutes, work in the middle of a feed or a wakeful 3am, and don&#39;t require quiet, stillness, or preparation.</p>\n<h2>Why Bother at All?</h2>\n<p>Mindfulness — paying attention to the present moment without judgment — has a robust evidence base for reducing stress and anxiety. The mechanisms are relevant for new parents: it activates the parasympathetic nervous system (reducing the fight-or-flight response that chronic stress keeps triggered), reduces rumination (the cycling thought loops that make exhaustion worse), and creates small moments of genuine rest even without sleep.</p>\n<p>Small consistent doses work better than occasional long sessions. Five minutes a day across a week produces measurable changes; one 35-minute session doesn&#39;t.</p>\n<h2>Practices That Actually Work in the Newborn Phase</h2>\n<h3>Breath Anchoring (2–3 minutes)</h3>\n<p>During a feed, instead of reaching for your phone, try anchoring your attention on your breath. You don&#39;t need to breathe differently — just notice it. Feel the air enter your nose, feel your chest or belly expand, feel the exhale.</p>\n<p>When your mind wanders (it will, constantly), notice that it&#39;s wandered and gently return to the breath. That return is the practice. You&#39;re not doing it wrong when your mind wanders — the repetition of returning is what builds the skill.</p>\n<p>This works during overnight feeds, during rocking, during any moment where you&#39;re present but not required to speak or think.</p>\n<h3>Sensory Grounding (1–2 minutes)</h3>\n<p>When anxiety or overwhelm spikes — the spiral of &quot;what if something&#39;s wrong, what if I&#39;m doing this wrong, I&#39;m so tired&quot; — sensory grounding interrupts the loop.</p>\n<p>The 5-4-3-2-1 technique: name (in your head or out loud) 5 things you can see, 4 you can hear, 3 you can touch and feel the sensation of, 2 you can smell, 1 you can taste. By the time you&#39;ve completed the list, your nervous system has typically settled somewhat.</p>\n<p>This works in the middle of the night, in a moment of parenting frustration, or whenever the anxiety is more than you can sit with.</p>\n<h3>The Single Mindful Task</h3>\n<p>Instead of using cooking, a shower, or a brief walk as a mental break (which often means replaying worries), use it as intentional mindfulness practice. Choose one sensory element and keep returning your attention to it.</p>\n<p>In the shower: just notice the temperature of the water, the sensation on your skin, the sound. When your mind goes to the to-do list or the last difficult feed, notice and return.</p>\n<p>It&#39;s not relaxing in the conventional sense. It&#39;s restful in the neurological sense — a genuine break from the constant mental commentary.</p>\n<h3>Compassionate Self-Talk (30 seconds)</h3>\n<p>The inner voice of new parents is often harsh: &quot;I should be coping better. Other parents manage. I&#39;m so bad at this.&quot; That voice contributes significantly to anxiety and low mood.</p>\n<p>A simple practice: when you notice the harsh voice, try responding to yourself the way you&#39;d respond to a good friend in the same situation. What would you actually say to someone you love who was this tired and this overwhelmed? That&#39;s what you deserve to hear from yourself.</p>\n<h2>Apps Worth Noting</h2>\n<p>If you want guided support, apps like Headspace, Calm, and Insight Timer all have short 5–10 minute sessions suited to the limited time windows of new parenthood. Headspace has a specific &quot;parenting&quot; section. You don&#39;t need a subscription to access basic sessions on most platforms.</p>\n<h2>Bottom Line</h2>\n<p>You won&#39;t establish a daily meditation practice in the newborn phase and that&#39;s fine. What you can do is bring occasional moments of present-moment attention to the chaos — during a feed, in a shower, in the 60 seconds before you respond to a cry. That&#39;s enough to make a difference.</p>\n"
}